.gitignore
AUTHORS.rst
CHANGELOG.rst
CODE_OF_CONDUCT.rst
CONTRIBUTING.rst
LICENSE
MANIFEST.in
README.rst
requirements.txt
setup.cfg
setup.py
outlyer/__init__.py
outlyer.plugin_helper.egg-info/PKG-INFO
outlyer.plugin_helper.egg-info/SOURCES.txt
outlyer.plugin_helper.egg-info/dependency_links.txt
outlyer.plugin_helper.egg-info/requires.txt
outlyer.plugin_helper.egg-info/top_level.txt
outlyer/plugin_helper/__init__.py
outlyer/plugin_helper/container/__init__.py
outlyer/plugin_helper/container/_mongo.py
outlyer/plugin_helper/container/_nginx.py
outlyer/plugin_helper/container/_postgres.py
outlyer/plugin_helper/container/_requests.py
outlyer/plugin_helper/container/_socket.py
outlyer/plugin_helper/container/_subprocess.py
tests/__init__.py
tests/test_docker.py
tests/test_subprocess.py