Metadata-Version: 1.1
Name: outlyer.plugin-helper
Version: 0.0.12
Summary: Outlyer plugin helper
Home-page: https://github.com/outlyerapp/plugin_helper
Author: Colin Hemmings
Author-email: colin.hemmings@outlyer.com
License: MIT
Download-URL: https://github.com/outlyerapp/plugin_helper/archive/0.9.tar.gz
Keywords: outlyer,plugin,helper
Platform: UNKNOWN
Classifier: Development Status :: 5 - Production/Stable
Classifier: Intended Audience :: Developers
Classifier: Natural Language :: English
Classifier: License :: OSI Approved :: MIT License
Classifier: Operating System :: OS Independent
Classifier: Programming Language :: Python
Classifier: Programming Language :: Python :: 2
Classifier: Programming Language :: Python :: 2.6
Classifier: Programming Language :: Python :: 2.7
Classifier: Programming Language :: Python :: 3
Classifier: Programming Language :: Python :: 3.3
Classifier: Programming Language :: Python :: 3.4
Classifier: Programming Language :: Python :: 3.5
Classifier: Programming Language :: Python :: Implementation :: CPython
Classifier: Programming Language :: Python :: Implementation :: PyPy
Classifier: Topic :: Software Development :: Libraries :: Python Modules
